torchvision/__init__.py
torchvision/utils.py
torchvision/datasets/__init__.py
torchvision/datasets/cifar.py
torchvision/datasets/coco.py
torchvision/datasets/fakedata.py
torchvision/datasets/folder.py
torchvision/datasets/lsun.py
torchvision/datasets/mnist.py
torchvision/datasets/omniglot.py
torchvision/datasets/phototour.py
torchvision/datasets/semeion.py
torchvision/datasets/stl10.py
torchvision/datasets/svhn.py
torchvision/datasets/utils.py
torchvision/models/__init__.py
torchvision/models/alexnet.py
torchvision/models/densenet.py
torchvision/models/inception.py
torchvision/models/resnet.py
torchvision/models/squeezenet.py
torchvision/models/vgg.py
torchvision/transforms/__init__.py
torchvision/transforms/functional.py
torchvision/transforms/transforms.py
torchvision_raspi-0.2.1.1.dist-info/DESCRIPTION.rst
torchvision_raspi-0.2.1.1.dist-info/LICENSE.txt
torchvision_raspi-0.2.1.1.dist-info/METADATA
torchvision_raspi-0.2.1.1.dist-info/RECORD
torchvision_raspi-0.2.1.1.dist-info/WHEEL
torchvision_raspi-0.2.1.1.dist-info/metadata.json
torchvision_raspi-0.2.1.1.dist-info/top_level.txt
torchvision_raspi-0.2.1.1.dist-info/zip-safe
