Metadata-Version: 2.0
Name: torchvision-raspi
Version: 0.2.1.1
Summary: Torchvision for Raspberry Pi 3B armv7l
Home-page: https://github.com/pytorch/vision
Author: PyTorch Core Team
Author-email: soumith@pytorch.org
License: BSD
Platform: UNKNOWN
Requires-Dist: pillow (>=4.1.1)
Requires-Dist: six
Requires-Dist: torch-raspi
Requires-Dist: tqdm
